fl_manager/core/__init__.py
fl_manager/core/component.py
fl_manager/core/constants.py
fl_manager/core/meta_registry.py
fl_manager/core/py.typed
fl_manager/core/components/__init__.py
fl_manager/core/components/checkers/__init__.py
fl_manager/core/components/checkers/dataset_checker.py
fl_manager/core/components/checkers/dataset_checker_registry.py
fl_manager/core/components/checkers/base/__init__.py
fl_manager/core/components/checkers/base/is_instance.py
fl_manager/core/components/datasets/__init__.py
fl_manager/core/components/datasets/dataframe_dataset.py
fl_manager/core/components/datasets/dataframe_dataset_registry.py
fl_manager/core/components/distributors/__init__.py
fl_manager/core/components/distributors/dataset_distributor.py
fl_manager/core/components/distributors/dataset_distributor_registry.py
fl_manager/core/components/distributors/base/__init__.py
fl_manager/core/components/distributors/base/dirichlet_dataset_distributor.py
fl_manager/core/components/distributors/base/iid_dataset_distributor.py
fl_manager/core/components/formatters/__init__.py
fl_manager/core/components/formatters/dataset_formatter.py
fl_manager/core/components/formatters/dataset_formatter_registry.py
fl_manager/core/components/formatters/dataset_formatter_runner.py
fl_manager/core/components/formatters/base/__init__.py
fl_manager/core/components/formatters/base/column_dropper_formatter.py
fl_manager/core/components/formatters/base/column_explode_formatter.py
fl_manager/core/components/formatters/base/column_rename_formatter.py
fl_manager/core/components/formatters/base/dict_extractor_formatter.py
fl_manager/core/components/models/__init__.py
fl_manager/core/components/models/fl_model.py
fl_manager/core/components/models/fl_model_registry.py
fl_manager/core/components/preprocessors/__init__.py
fl_manager/core/components/preprocessors/dataset_preprocessor.py
fl_manager/core/components/preprocessors/dataset_preprocessor_registry.py
fl_manager/core/components/readers/__init__.py
fl_manager_core-0.1.0.dist-info/METADATA
fl_manager_core-0.1.0.dist-info/WHEEL
fl_manager_core-0.1.0.dist-info/licenses/LICENSE
fl_manager_core-0.1.0.dist-info/RECORD
